{
  "name": "村民",
  "icon": "minecraft:emerald",
  "category": "biota",
  "pages": [
    {
      "type": "text",
      "text": "兰金计划加入了一些全新的市场交易，可拿无用的资源换来坚硬的绿宝石，也可以此购买较难获得的资源。原有的村民新增了部分杂项交易，但大部分新交易都为新职业所独有。"
    },
    {
      "type": "crafting",
      "recipe": "rankine:nickel_silver_coin",
      "recipe2": "rankine:sterling_silver_coin",
      "title": "通用硬币"
    },
    {
      "type": "entity",
      "entity": "minecraft:villager{VillagerData:{profession:'rankine:mineralogist'}}",
      "name": "矿物学家",
      "text": "工作站点方块：合金模板台"
    },
    {
      "type": "entity",
      "entity": "minecraft:villager{VillagerData:{profession:'rankine:metallurgist'}}",
      "name": "冶金学家",
      "text": "工作站点方块：活塞式粉碎机"
    },
    {
      "type": "entity",
      "entity": "minecraft:villager{VillagerData:{profession:'rankine:botanist'}}",
      "name": "植物学家",
      "text": "工作站点方块：植物学家工作站"
    },
    {
      "type": "entity",
      "entity": "minecraft:villager{VillagerData:{profession:'rankine:gem_cutter'}}",
      "name": "宝石切割匠",
      "text": "工作站点方块：金刚石压砧"
    },
    {
      "type": "entity",
      "entity": "minecraft:villager{VillagerData:{profession:'rankine:rock_collector'}}",
      "name": "岩石收藏家",
      "text": "工作站点方块：沉积桨扇"
    }
  ]
}