{
  "assigned_items": [],
  "icon": {
    "count": 1,
    "id": "enchanted:circle_talisman"
  },
  "pages": [
    {
      "components": [
        {
          "header": "Talisman",
          "template": "modopedia:page/headered_text",
          "text": "$(b)$(el:items/circle_talisman)Circle talismans$(/el)$(/b) can be used to easily pick up and move glyphs, reducing wasted chalk.\n\nThe bound talisman can be used on the ground to place the glyphs it holds.\n\nWorks with any and all glyphs."
        }
      ]
    },
    {
      "components": [
        {
          "components": [
            {
              "rite": "enchanted:bind_talisman",
              "template": "enchanted:page/rite"
            },
            {
              "rite": "enchanted:bind_talisman_charged",
              "template": "enchanted:page/rite"
            }
          ]
        }
      ]
    }
  ],
  "title": "Talisman"
}