{
  "name": "经验手册",
  "icon": "bloodmagic:experiencebook",
  "category": "bloodmagic:utility",
  "pages": [
    {
      "type": "patchouli:text",
      "text": "$(item)经验手册$()允许你安全储存你的$(thing)经验值$()。$(br2)手持时按[$(k:sneak)]和[$(k:use)]储存$(thing)1级经验$()。按[$(k:use)]$(thing)取回1级经验$()。摁住[$(k:use)]$(thing)批量存取经验$()。"
    },
    {
      "type": "patchouli:crafting",
      "recipe": "bloodmagic:experience_tome"
    },
    {
      "type": "patchouli:text",
      "flag": "mod:curios",
      "text": "当你安装了$(thing)饰品$()，你可以在护符槽位装备此$(item)经验手册$()。如果你想要佩戴更多的印记饰品，建议使用$(l:bloodmagic:alchemy_array/sigil/holding)集持印记$()，或者为你的$(l:bloodmagic:alchemy_array/living_equipment/living_basics)束灵盔甲$()增加$(l:bloodmagic:alchemy_array/living_equipment/armor_upgrades/curios_sockets)槽位升级$()。"
    }
  ]
}
