{
    "name": "Minke Whale" , 
    "icon": "untamedwilds:textures/icon/baleen_whale/minke.png" , 
    "category": "untamedwilds:baleen_whale_category" , 
    "pages": [
        {
            "type": "text" , 
            "title": "Minke Whale" , 
            "text": "The common minke whale or northern minke whale ($(o)Balaenoptera acutorostrata$()) is a species of minke whale within the suborder of baleen whales.$(br2)It is the smallest species of the rorquals and the second smallest species of baleen whale."
        } , 
        {
            "type": "entity" , 
            "entity": "untamedwilds:baleen_whale{Variant: 4, Size: 1}" , 
            "text": ""
        } , 
        {
            "type": "text" , 
            "title": "Minke Whale" , 
            "text": "Relative Size: \u2605\u2605\u2605\u2606\u2606$(br2)Always active$(br2)1 Colors$(br2)Favourite Food: untamedwilds:chum$(br2)Number of Offspring: 1$(br2)Growth time: 12 Days"
        }
    ]
}