{
  "name": "一般生物群系",
  "icon": "twilightforest:magic_map_empty",
  "category": "biomes",
  "advancement": "twilightforest:alt/biomes/general_biomes",
  "sortnum": 1000,
  "pages": [
    {
      "type": "text",
      "text": "一般生物群落信息。这些生物群落并不特别。"
    }, {
      "type": "text",
      "advancement": "twilightforest:alt/biomes/twilight_forest",
      "text": "暮色森林"
    }, {
      "type": "text",
      "advancement": "twilightforest:alt/biomes/firefly_forest",
      "text": "萤火虫森林"
    }, {
      "type": "text",
      "advancement": "twilightforest:alt/biomes/twilight_clearing",
      "text": "暮色空地"
    }, {
      "type": "text",
      "advancement": "twilightforest:alt/biomes/oak_savannah",
      "text": "橡木热带草原"
    }, {
      "type": "text",
      "advancement": "twilightforest:alt/biomes/dense_twilight_forest",
      "text": "繁密暮色森林"
    }, {
      "type": "text",
      "advancement": "twilightforest:alt/biomes/mushroom_forest",
      "text": "蘑菇森林"
    }, {
      "type": "text",
      "advancement": "twilightforest:alt/biomes/deep_mushroom_forest",
      "text": "蘑菇深林"
    }, {
      "type": "text",
      "advancement": "twilightforest:alt/biomes/twilight_lake",
      "text": "这些湖泊包含了什么是一个谜。这些湖泊除了水量丰富，似乎没有什么特别之处。传说有一天湖中可能会出现一座岛屿。谁知道它会装什么?"
    }
  ]
}