{
    "name": "Clown Triggerfish" , 
    "icon": "untamedwilds:textures/icon/triggerfish/clown.png" , 
    "category": "untamedwilds:triggerfish_category" , 
    "pages": [
        {
            "type": "text" , 
            "title": "Clown Triggerfish" , 
            "text": "The clown triggerfish ($(o)Balistoides conspicillum$()), also known as the bigspotted triggerfish, is a demersal marine fish belonging to the family Balistidae, or commonly called triggerfish."
        } , 
        {
            "type": "entity" , 
            "entity": "untamedwilds:triggerfish{Variant: 0, Size: 1}" , 
            "text": ""
        } , 
        {
            "type": "text" , 
            "title": "Clown Triggerfish" , 
            "text": "Relative Size: \u2605\u2605\u2605\u2606\u2606$(br2)Always active$(br2)1 Colors$(br2)Favourite Food: untamedwilds:chum$(br2)Number of Offspring: 4$(br2)Growth time: 6 Days"
        }
    ]
}