{
    "name": "Ornamental Tree Spider" , 
    "icon": "untamedwilds:textures/icon/tarantula/regalis.png" , 
    "category": "untamedwilds:tarantula_category" ,
    "pages": [
        {
            "type": "text" , 
            "title": "Ornamental Tree Spider" , 
            "text": "Poecilotheria regalis is a species of arboreal tarantula and is found in parts of India.$(br2)The common name for this spider is Indian ornamental tree spider, or simply Indian ornamental.$(br2)It is one of the most popular arboreal tarantulas for amateur collectors."
        } , 
        {
            "type": "entity" , 
            "entity": "untamedwilds:tarantula{Variant: 5, Size: 1}" ,
            "text": ""
        }
    ]
}