{
    "name": "Tidal Ring",
    "icon": "turtlemancy:tidal_ring",
    "category": "turtlemancy:equipment",
    "pages": [
        {
            "type": "spotlight",
            "title": "Tidal Ring",
        	"item": "turtlemancy:tidal_ring",
            "text": "This $(thing)curio$() will change the effect of the $(thing)Bubble Leviosa$() spell, instead of healing, it will deal damage."
        },
        {
            "type": "crafting",
            "recipe": "turtlemancy:tidal_ring",
            "link_recipe": true
        }
    ]
}