{
    "name": "Improper Spells",
    "icon": "turtlemancy:dark_turtlemancer_wand",
    "category": "turtlemancy:spells",
    "pages": [
        {
            "type": "spotlight",
            "title": "Advanced Spells",
        	"item": "turtlemancy:dark_turtlemancer_wand",
            "text": "A compendium of the spells that only the dark wands can cast. $(br2)(This wand can also perform the apprentice spells except bubble related and defense)."
        },
        {
            "type": "image",
            "title": "Lava Bubble",
        	"images":[ 
        			"turtlemancy:textures/book/lava_bubble.png"
        	],
        	"border": true,
            "text": "Drags your target towards you. Also, heals it."
        },
        {
            "type": "image",
            "title": "Self Lava Bubble I",
            "images":[ 
        			"turtlemancy:textures/book/self_lava_bubble.png"
        	],
        	"border": true,
            "text": "Pressing $(k:turtlemancy.selfbubble) you can go into the direction you are looking."
        },
        {
            "type": "spotlight",
            "title": "Trader Burst",
        	"item": "minecraft:emerald",
            "text": "There is nothing more anoying than the Wandering Trader. Proper Turtlemancer are always so nice to everyone... $(br)Not like us, some badass Improper Turtlemancers... Make him explode! Free emeralds! No one wants his useless trades anyways! Make him explode!"
        },
        {
            "type": "text",
            "title": "Evil Defense",
            "text": "Use the wand while sneaking to get $(thing)Fire Resistance II$() at the cost of getting $(thing)Slowness I$()."
        }
    ],
    "sortnum": 5
}