{
    "name": "Glowing Bee",
    "icon": "minecraft:glowstone_dust",
    "read_by_default": true,
    "category": "productivebees:bees_wild",
    "pages": [
        {
            "type": "patchouli:text",
            "title": "Glowing Bee",
            "text": "Found living in glowing nests in the nether. Glowing Bees prefer pollinating glowing blocks like glowstone or lamps.",
            "anchor": "glowing"
        },
        {
            "type": "patchouli:entity",
            "entity": "productivebees:configurable_bee{type:'productivebees:glowing'}"
        }
    ]
}