{
  "name": "Music Sheet of the Gnome King",
  "icon": "terramity:music_sheet_of_the_gnome_king",
  "category": "terramity:ocarina",
  "sortnum": 30,
  "pages": [
    {
      "type": "patchouli:spotlight",
	  "title": "Music Sheet of the Gnome King",
	  "text": "The Music Sheet of the Gnome King grants Haste II for 120 seconds.$(br2)This sheet is dropped by Gob, King of Gnomes.",
	  "item": {
		"item": "terramity:music_sheet_of_the_gnome_king"
	  }
    },
	{
      "type": "patchouli:image",
      "title": "Music Sheets",
      "images": ["terramity:textures/screens/music_sheets.png"],
      "border": true
    }
  ]
}