{
  "name": "食物",
  "icon": "complicated_bees:ambrosia",
  "category": "complicated_bees:other",
  "advancement": "complicated_bees:recipes/honey_bread",
  "pages": [
    {
      "type": "patchouli:text",
      "text": "蜂蜜及其相关产物可用来制作多种食物。"
    },
    {
      "type": "patchouli:crafting",
      "recipe": "complicated_bees:honey_bread",
      "recipe2": "complicated_bees:honey_porkchop"
    },
    {
      "type": "patchouli:crafting",
      "recipe": "complicated_bees:ambrosia",
      "title": "神的食物",
      "text": "食用后给予生命恢复、跳跃提升，以及伤害吸收。"
    }
  ]
}