{
  "name": "Crafting Spellbooks",
  "icon": "minecraft:writable_book",
  "category": "scriptor:crafting",
  "pages": [
    {
      "type": "patchouli:text",
      "text": [
        "A Spellbook can be crafted by writing a book, then combining it with a Spellbook Binder ",
        "in a crafting grid.",
        "$(br2)",
        "Similarly, any normal Spellbook can be crafted back into a Written Book ",
        "by combining it in a crafting grid with a Leather Binder."
      ]
    },
    {
      "type": "patchouli:crafting",
      "title": "Book Binders",
      "recipe": "scriptor:leather_binder",
      "recipe2": "scriptor:spellbook_binder"
    }
  ]
}