{
  "name": "Making a Dispatcher Nidus",
  "icon": "srpcotesia:nidus_accumulator",
  "category": "items",
  "pages": [
    {
      "type": "spotlight",
      "link_recipe": true,
      "item": "srpcotesia:nidus_accumulator",
      "text": "$(#630000)Under normal circumstances, a parasite will create a Dispatcher Nidus occasionally once it reaches 15 kills. This is not only unreliable, however, but it also takes a long time to get them to do it, and unfortunately it appears I can't make my own this way."
    },
    {
      "type": "text",
      "text": "$(#630000)Instead, I can craft a Nidus Accumulator and feed it the kills instead. Nidus Accumulators will store any kills I obtain as I travel, transforming into a Dispatcher Nidus once I collect 15. It only works in the hotbar."
    },
    {
      "type": "crafting",
      "recipe": "srpcotesia:nidus_accumulator",
      "recipe2": "srpcotesia:nidus_accumulator_alt1"
    },
    {
      "type": "crafting",
      "recipe": "srpcotesia:nidus_accumulator_alt2"
    }
  ]
}