{
    "name": "龙蛋蜂箱",
    "icon": "productivebees:dragon_egg_hive",
    "category": "productivebees:hives",
    "sortnum": 4,
    "pages": [
        {
            "type": "patchouli:spotlight",
            "item": "productivebees:dragon_egg_hive",
            "text": "一种为末影龙蜜蜂设计的特殊蜂箱，使得使用者可以收获到原本难以获得的末影龙蜜脾。通常末影龙蜜蜂生活在黑曜石蜂巢中，但也会生活在掏空的龙蛋中。它们也可以被说服住在高级蜂巢中，但不会产生任何龙息。"
        },
        {
            "type": "patchouli:crafting",
            "recipe": "productivebees:nests/dragon_egg_hive",
            "text": "你可以用掏空的部分做一份丰盛的煎蛋卷。"
        },
        {
            "type": "patchouli:text",
            "text": "生活在末地的龙蛋蜂巢中的末影龙蜜蜂不需要采蜜，因为它们会从空气中吸收到末影龙的精华。当在任意其他蜂巢工作时，末影龙蜜蜂就必须有另一个授粉来源。$(br2)龙蛋蜂箱不支持升级。"
        }
    ]
}