{
    "name": "外部火焰加热器",
    "icon": "naturesaura:furnace_heater",
    "category": "using",
    "advancement": "naturesaura:infused_materials",
    "pages": [
        {
            "type": "text",
            "text": "在某种程度上，$(item)熔炉$()的效率可谓极其低下。$(br)$(item)外部火焰加热器$()可以加速其所附着的$(item)熔炉$()，给它必要的热能以精炼所有材料。需要注意的是，既然此过程会消耗$(#419600)灵气$()，自然灵气水平可能会过低，造成$(l:intro/aura)收益减少$()."
        },
        {
            "type": "naturesaura:tree_ritual",
            "text": "通过$(l:practices/tree_ritual)森林仪式$()创造$(item)外部火焰加热器$()",
            "recipe": "naturesaura:furnace_heater"
        }
    ]
}
