{
  "name": "泥土桶",
  "read_by_default": "true",
  "icon": "dynamictrees:dirt_bucket",
  "category": "dynamictrees:mechanics",
  "sortnum": 1,
  "pages": [
    {
      "type": "spotlight",
      "item": "dynamictrees:dirt_bucket",
      "title": "泥土桶",
      "link_recipe": true,
      "text": "泥土桶可用于互换种子和树苗。$(br2)将种子或树苗和泥土桶放入工作台即可转换。此配方为无序配方。"
    },
    {
      "type": "crafting",
      "title": "泥土桶",
      "anchor": "dirt_bucket",
      "recipe": "dynamictrees:dirt_bucket",
      "text": "将泥土和桶组合即可获得泥土桶。$(br2)如有需要，对地面右击可清空桶。"
    },
    {
      "type": "crafting",
      "title": "种子至树苗",
      "recipe": "dynamictrees:oak_seed_to_minecraft_oak_sapling",
      "recipe2": "dynamictrees:minecraft_oak_sapling_to_oak_seed"
    },
    {
      "type": "crafting",
      "title": "果实至种子",
      "recipe": "dynamictrees:minecraft_apple_to_apple_oak_seed",
      "text": "果树不会掉落种子，而是可以从掉落的果实中获取。"
    }
  ]
} 