{
  "name": "Time Magic",
  "icon": "minecraft:clock",
  "category": "rituals/summoning",
  "sortnum": 31,
  "pages": [
    {
      "type": "text",
      "text": "Time magic is limited in scope, it cannot send the magician back or forth in time, but rather allows to change time time of day. This is especially useful for rituals or other tasks requiring day or nighttime specifically."
    },
    {
      "type": "summoning",
      "heading": "Summoning of Dawn",
      "pentacle": "$(l:pentacles/summon_djinni)Ophyx' Calling$(/l)",
      "activation_item": "occultism:book_of_binding_bound_djinni",
      "ingredients": "$(li)1x $(item)Torch $()$(li)1x $(item)Any Sapling $()$(li)1x $(item)Wheat $()$(li)1x $(item)Any Yellow Dye $()"
    },
    {
      "type": "summoning",
      "heading": "Summoning of Dusk",
      "pentacle": "$(l:pentacles/summon_djinni)Ophyx' Calling$(/l)",
      "activation_item": "occultism:book_of_binding_bound_djinni",
      "ingredients": "$(li)1x $(item)Any Bed $()$(li)1x $(item)Rotten Flesh $()$(li)1x $(item)Bone $()$(li)1x $(item)Any Black Dye $()"
    },
    {
      "type": "empty",
      "draw_filler": false
    }
  ]
}

