{
    "providers":[
        {
            "type":"bitmap",
            "file": "minecraft:font/cjk_punctuations.png",
            "ascent": 7,
            "chars": [
                "\u3001\u3002\u300a\u300b\u3010\u3011\u2018\u2019\u201c\u0000\u3008\u3009\u0000\u0000\u0000\u0000",
                "\u201d\uff01\uff08\uff09\uff0c\uff1a\uff1b\uff1f\u2014\u00b7\u0000\u0000\u0000\u0000\u0000\u0000"
            ]
        },
        {
            "type":"bitmap",
            "file": "minecraft:font/ellipsis.png",
            "ascent": 7,
            "chars": [
                "\u22ef"
            ]
        },
        {
            "type": "bitmap",
            "file": "minecraft:font/2em-dash.png",
            "ascent": 7,
            "chars": [
                "\u2e3a"
            ]
        }
    ]
}